{"spx": {"price": "7,408", "change": -1.24}, "ftse": {"price": "10,195", "change": -1.71}, "dax": {"price": "23,951", "change": -2.07}, "omxspi": {"price": "1,061", "change": -0.32}, "omxs30": {"price": "3,036", "change": -0.38}, "nikkei": {"price": "61,409", "change": -2.12}, "bchusd": {"price": "416.04", "change": -2.42}, "eurusd": {"price": "1.1631"}, "gbpusd": {"price": "1.3324"}, "eurchf": {"price": "0.9142"}, "eurjpy": {"price": "184.56"}, "usdchf": {"price": "0.786"}, "usdjpy": {"price": "158.73"}, "usdsek": {"price": "9.4349"}, "usddkk": {"price": "6.4258"}, "usdnok": {"price": "9.3056"}, "usdcop": {"price": "3791.48"}, "sekcop": {"price": "402"}}